certmonitor-0.1.4.dist-info/METADATA
certmonitor-0.1.4.dist-info/WHEEL
certmonitor-0.1.4.dist-info/licenses/LICENSE
certmonitor/__init__.py
certmonitor/certinfo.abi3.so
certmonitor/certinfo.pyi
certmonitor/cipher_algorithms.py
certmonitor/config.py
certmonitor/core.py
certmonitor/error_handlers.py
certmonitor/protocol_handlers/base.py
certmonitor/protocol_handlers/ssh_handler.py
certmonitor/protocol_handlers/ssl_handler.py
certmonitor/utils/__init__.py
certmonitor/utils/utils.py
certmonitor/validators/__init__.py
certmonitor/validators/base.py
certmonitor/validators/expiration.py
certmonitor/validators/hostname.py
certmonitor/validators/key_info.py
certmonitor/validators/root_certificate_validator.py
certmonitor/validators/subject_alt_names.py
certmonitor/validators/tls_version.py
certmonitor/validators/weak_cipher.py
certmonitor-0.1.4.dist-info/RECORD
