Metadata-Version: 2.4
Name: certmonitor
Version: 0.1.4
License-File: LICENSE
Summary: A simple package to parse certificates
Author-email: Brad Haas <bradh11@gmail.com>
License: MIT
Requires-Python: >=3.8, <3.14
